fragscan_ct/__init__.py
fragscan_ct/__main__.py
fragscan_ct/calculate_fragment_length_ratio.py
fragscan_ct/lowess.py
fragscan_ct/main.py
fragscan_ct/merge_intervals.py
fragscan_ct/pad_coordinates.py
fragscan_ct/read_bed.py
fragscan_ct-0.1.0.dist-info/LICENSE
fragscan_ct-0.1.0.dist-info/METADATA
fragscan_ct-0.1.0.dist-info/WHEEL
fragscan_ct-0.1.0.dist-info/entry_points.txt
fragscan_ct-0.1.0.dist-info/RECORD
