Metadata-Version: 2.1
Name: fragscan_ct
Version: 0.1.0
Summary: This Python package, is designed to calculate the fragment length ratios from a BAM file using the input BED and reference genome files. The script provides several options for manipulating the input intervals and applying GC content correction to the coverage analysis.
Author: Ronak Shah
Author-email: shahr2@mskcc.org
Requires-Python: >=3.9,<4.0
Classifier: Programming Language :: Python :: 3
Classifier: Programming Language :: Python :: 3.9
Classifier: Programming Language :: Python :: 3.10
Classifier: Programming Language :: Python :: 3.11
Classifier: Programming Language :: Python :: 3.12
Requires-Dist: numpy (>=2.0.0,<3.0.0)
Requires-Dist: pandas (>=2.2.2,<3.0.0)
Requires-Dist: plotly (>=5.22.0,<6.0.0)
Requires-Dist: scipy (>=1.7.3,<2.0.0)
Requires-Dist: statsmodels (>=0.14.2,<0.15.0)
Requires-Dist: typer[all] (>=0.12.3,<0.13.0)
